bayes_opt/__init__.py
bayes_opt/acquisition.py
bayes_opt/bayesian_optimization.py
bayes_opt/constraint.py
bayes_opt/domain_reduction.py
bayes_opt/exception.py
bayes_opt/logger.py
bayes_opt/parameter.py
bayes_opt/py.typed
bayes_opt/target_space.py
bayes_opt/util.py
bayesian_optimization-3.0.1.dist-info/LICENSE
bayesian_optimization-3.0.1.dist-info/METADATA
bayesian_optimization-3.0.1.dist-info/WHEEL
bayesian_optimization-3.0.1.dist-info/RECORD
