Metadata-Version: 2.3
Name: bayesian-optimization
Version: 3.0.1
Summary: Bayesian Optimization package
License: The MIT License (MIT)
Author: Fernando Nogueira
Author-email: fmfnogueira@gmail.com
Requires-Python: >=3.9,<4.0
Classifier: License :: OSI Approved :: MIT License
Classifier: Programming Language :: Python
Classifier: Programming Language :: Python :: 3
Classifier: Programming Language :: Python :: 3.9
Classifier: Programming Language :: Python :: 3.10
Classifier: Programming Language :: Python :: 3.11
Classifier: Programming Language :: Python :: 3.12
Classifier: Programming Language :: Python :: 3.13
Requires-Dist: colorama (>=0.4.6,<1.0.0)
Requires-Dist: numpy (>=1.25) ; python_version < "3.13"
Requires-Dist: numpy (>=2.1.3) ; python_version >= "3.13"
Requires-Dist: scikit-learn (>=1.0.0,<2.0.0)
Requires-Dist: scipy (>=1.0.0,<2.0.0) ; python_version < "3.13"
Requires-Dist: scipy (>=1.14.1,<2.0.0) ; python_version >= "3.13"
